infra_operator/__init__.py
infra_operator/cli.py
infra_operator/clients/__init__.py
infra_operator/clients/ghe.py
infra_operator/clients/mod.py
infra_operator/create/__init__.py
infra_operator/create/aws_appmesh.py
infra_operator/create/aws_elbv2_create.py
infra_operator/create/aws_secretsmanager.py
infra_operator/create/mod.py
infra_operator/delete/__init__.py
infra_operator/delete/aws_iam_delete.py
infra_operator/delete/mod.py
infra_operator/diff/__init__.py
infra_operator/diff/mod.py
infra_operator/export/aws_elbv2_export.py
infra_operator/export/mod.py
infra_operator/layout/__init__.py
infra_operator/layout/mod.py
infra_operator/operators/mod.py
infra_operator/output/mod.py
infra_operator/plugins/mod.py
infra_operator/plugins/wea_notify.py
infra_operator/preprocess/__init__.py
infra_operator/preprocess/mod.py
infra_operator/preprocess/verify.py
infra_operator/read/mod.py
infra_operator/update/__init__.py
infra_operator/update/aws_iam_update.py
infra_operator/update/aws_sg_update.py
infra_operator/update/ghe_update.py
infra_operator/update/mod.py
infra_operator/utils/__init__.py
infra_operator/utils/config.py
infra_operator/utils/dump.py
infra_operator/utils/load.py
infra_operator/utils/mod.py
infra_operator/validate/mod.py
infra_operator-1.0.23.dist-info/METADATA
infra_operator-1.0.23.dist-info/WHEEL
infra_operator-1.0.23.dist-info/licenses/LICENSE
infra_operator-1.0.23.dist-info/RECORD
