Metadata-Version: 2.1
Name: infra-operator
Version: 1.0.23
Summary: Turn apis into declarative yaml files
Project-URL: Homepage, https://git.toolsfdg.net/devops/infra-operator
Project-URL: Bug Tracker, https://git.toolsfdg.net/devops/infra-operator/issues
Author-email: Desmond <desmond.cao@binance.com>
License-File: LICENSE
Classifier: License :: OSI Approved :: GNU General Public License v3 (GPLv3)
Classifier: Operating System :: OS Independent
Classifier: Programming Language :: Python :: 3
Requires-Python: >=3.7
Requires-Dist: boto3==1.26.65
Requires-Dist: oyaml==1.0
Requires-Dist: pygithub==1.57
